LICENSE
MANIFEST.in
README.md
pyproject.toml
setup.py
fivepoint_pynq/__init__.py
fivepoint_pynq.egg-info/PKG-INFO
fivepoint_pynq.egg-info/SOURCES.txt
fivepoint_pynq.egg-info/dependency_links.txt
fivepoint_pynq.egg-info/entry_points.txt
fivepoint_pynq.egg-info/not-zip-safe
fivepoint_pynq.egg-info/requires.txt
fivepoint_pynq.egg-info/top_level.txt
fivepoint_pynq/notebooks/introduction.ipynb
fivepoint_pynq/notebooks/client/client.ipynb
fivepoint_pynq/notebooks/client/demo.html
fivepoint_pynq/notebooks/client/get-demo-data.ipynb
fivepoint_pynq/notebooks/client/data/PLACE_DATA_HERE
fivepoint_pynq/notebooks/client/img/img-not-found.png
fivepoint_pynq/notebooks/client/img/open-raw.png
fivepoint_pynq/notebooks/client/img/pynq-logo.png
fivepoint_pynq/notebooks/client/img/xilinx-logo.png
fivepoint_pynq/notebooks/server/5point_nister.xclbin.link
fivepoint_pynq/notebooks/server/server.ipynb
fivepoint_pynq/notebooks/server/img/5-point_relpose.png
fivepoint_pynq/ransac/ransac.h
fivepoint_pynq/ransac/ransac_py.cpp
fivepoint_pynq/ransac/ransac_py.h