Metadata-Version: 2.1
Name: fivepoint-pynq
Version: 1.0
Summary: 5-point Relative Pose Problem for PYNQ
Home-page: https://github.com/Xilinx/5point-PYNQ
Author: Giuseppe Natale
Author-email: pynq_support@xilinx.com
License: Apache License 2.0
Download-URL: https://github.com/Xilinx/5point-PYNQ
Platform: UNKNOWN
Requires-Python: >=3.5.2
